{
    "@odata.context":"https://azs-playground.search.windows.net/$metadata#indexes/$entity",
    "name":"qcdocs",
    "fields":[
        {
            "name":"id",
            "type":"Edm.String",
            "searchable":false,
            "filterable":false,
            "retrievable":true,
            "sortable":false,
            "facetable":false,
            "key":true,
            "indexAnalyzer":null,
            "searchAnalyzer":null,
            "analyzer":null
        },
        {
            "name":"document_type",
            "type":"Edm.String",
            "searchable":true,
            "filterable":true,
            "retrievable":true,
            "sortable":true,
            "facetable":true,
            "key":false,
            "indexAnalyzer":null,
            "searchAnalyzer":null,
            "analyzer":null
        },
        {
            "name":"project_name",
            "type":"Edm.String",
            "searchable":true,
            "filterable":true,
            "retrievable":true,
            "sortable":true,
            "facetable":true,
            "key":false,
            "indexAnalyzer":null,
            "searchAnalyzer":null,
            "analyzer":"ja.microsoft"
        },
        {
            "name":"project_location",
            "type":"Edm.String",
            "searchable":true,
            "filterable":true,
            "retrievable":true,
            "sortable":true,
            "facetable":true,
            "key":false,
            "indexAnalyzer":null,
            "searchAnalyzer":null,
            "analyzer":"ja.microsoft"
        },
        {
            "name":"blob_path",
            "type":"Edm.String",
            "searchable":true,
            "filterable":true,
            "retrievable":true,
            "sortable":true,
            "facetable":false,
            "key":false,
            "indexAnalyzer":null,
            "searchAnalyzer":null,
            "analyzer":null
        },
        {
            "name":"ocr_content",
            "type":"Edm.String",
            "searchable":true,
            "filterable":true,
            "retrievable":true,
            "sortable":true,
            "facetable":false,
            "key":false,
            "indexAnalyzer":null,
            "searchAnalyzer":null,
            "analyzer":"ja.microsoft"
        },
        {
            "name":"additional_information",
            "type":"Edm.String",
            "searchable":true,
            "filterable":true,
            "retrievable":true,
            "sortable":true,
            "facetable":true,
            "key":false,
            "indexAnalyzer":null,
            "searchAnalyzer":null,
            "analyzer":"ja.microsoft"
        },
        {
            "name":"posting_yearmonth",
            "type":"Edm.String",
            "searchable":false,
            "filterable":true,
            "retrievable":true,
            "sortable":true,
            "facetable":true,
            "key":false,
            "indexAnalyzer":null,
            "searchAnalyzer":null,
            "analyzer":null
        },
        {
            "name":"posting_date",
            "type":"Edm.DateTimeOffset",
            "searchable":false,
            "filterable":true,
            "retrievable":true,
            "sortable":true,
            "facetable":true,
            "key":false,
            "indexAnalyzer":null,
            "searchAnalyzer":null,
            "analyzer":null
        },
        {
            "name":"post_until",
            "type":"Edm.DateTimeOffset",
            "searchable":false,
            "filterable":true,
            "retrievable":true,
            "sortable":true,
            "facetable":true,
            "key":false,
            "indexAnalyzer":null,
            "searchAnalyzer":null,
            "analyzer":null
        },
        {
            "name":"posting_updated",
            "type":"Edm.DateTimeOffset",
            "searchable":false,
            "filterable":true,
            "retrievable":true,
            "sortable":true,
            "facetable":true,
            "key":false,
            "indexAnalyzer":null,
            "searchAnalyzer":null,
            "analyzer":null
        },
        {
            "name":"process_date",
            "type":"Edm.DateTimeOffset",
            "searchable":false,
            "filterable":true,
            "retrievable":true,
            "sortable":true,
            "facetable":true,
            "key":false,
            "indexAnalyzer":null,
            "searchAnalyzer":null,
            "analyzer":null
        },
        {
            "name":"geo_location",
            "type":"Edm.GeographyPoint",
            "searchable":false,
            "filterable":true,
            "retrievable":true,
            "sortable":true,
            "facetable":false,
            "key":false,
            "indexAnalyzer":null,
            "searchAnalyzer":null,
            "analyzer":null
        },
        {
            "name":"tags",
            "type":"Collection(Edm.String)",
            "searchable":true,
            "filterable":true,
            "retrievable":true,
            "sortable":false,
            "facetable":true,
            "key":false,
            "indexAnalyzer":null,
            "searchAnalyzer":null,
            "analyzer":null
        }
    ],
    "scoringProfiles":[
        {
            "name":"qcdocScoringFeatured",
            "text":{
                "weights":{
                    "project_name":3.0,
                    "project_location":3.0
                }
            },
            "functions":[
                {
                    "fieldName":"posting_date",
                    "freshness":{
                        "boostingDuration":"P500D"
                    },
                    "interpolation":"linear",
                    "magnitude":null,
                    "distance":null,
                    "tag":null,
                    "type":"freshness",
                    "boost":3.0
                },
                {
                    "fieldName":"tags",
                    "freshness":null,
                    "interpolation":"linear"
                    ,"magnitude":null,
                    "distance":null,
                    "tag":{
                        "tagsParameter":"featuredParam"
                    },
                    "type":"tag",
                    "boost":10.0
                },
                {
                    "fieldName":"geo_location",
                    "freshness":null,
                    "interpolation":"linear",
                    "magnitude":null,
                    "distance":{
                        "referencePointParameter":"mapCenterParam",
                        "boostingDistance":5.0
                    },
                    "tag":null,
                    "type":"distance",
                    "boost":6.0
                }
            ],
            "functionAggregation":"sum"
        }
    ],
    "defaultScoringProfile":null,
    "corsOptions":{
        "allowedOrigins":["*"],
        "maxAgeInSeconds":300
    },
    "suggesters":[
        {
            "name":"sg",
            "searchMode":"analyzingInfixMatching",
            "sourceFields":[
                "document_type","project_name","project_location"
            ]
        }
    ],
    "analyzers":[],
    "tokenizers":[],
    "tokenFilters":[],
    "charFilters":[]
}